[
  {
    "name": "theme_info",
    "theme_name": "Go-To Skincare",
    "theme_author": "AMD",
    "theme_version": "1.0.0",
    "theme_documentation_url": "https:\/\/gotoskincare.com\/",
    "theme_support_url": "https:\/\/gotoskincare.com\/"
  },
  {
    "name": "🛒 Cart Clear",
    "settings": [
      {
        "type": "checkbox",
        "id": "clear_cart_on_first_visit",
        "label": "Enable Cart Clear",
        "info": "Clear cart on first visit"
      },
      {
        "type": "range",
        "id": "clear_cart_on_first_days",
        "label": "Clear Every X Days",
        "min": 1,
        "max": 30,
        "unit": "Day",
        "default": 7
      }
    ]
  },
  {
    "name": "🔒 VIP Access",
    "settings": [
      {
        "type": "paragraph",
        "content": "Any template that has a suffix of 'vip-access' will be locked down unless the customer is logged in and has the corect loyalty tag."
      },
      {
        "type": "header",
        "content": "Enable Access For..."
      },
      {
        "type": "checkbox",
        "id": "vip_access_tier1",
        "label": "Tier 1 (Mate)"
      },
      {
        "type": "checkbox",
        "id": "vip_access_tier2",
        "label": "Tier 2 (Friend)"
      },
      {
        "type": "checkbox",
        "id": "vip_access_tier3",
        "label": "Tier 3 (Bestie)"
      },
      {
        "type": "checkbox",
        "id": "vip_access_tier4",
        "label": "Tier 4 (BFF)"
      },
      {
        "type": "checkbox",
        "id": "vip_access_tier5",
        "label": "Tier 5 (Peach)"
      },
      {
        "type": "checkbox",
        "id": "vip_access_staff",
        "label": "Staff"
      }
    ]
  },
  {
    "name": "👨‍💻 Custom Features",
    "settings": [
      {
        "type": "checkbox",
        "id": "enable_compact_mobile_header",
        "label": "Enable Compact Mobile Header",
        "default": true
      }
    ]
  },
  {
    "name": "🟪 Colors (Go-To)",
    "settings": [
      {
        "type": "header",
        "content": "General"
      },
      {
        "type": "color",
        "id": "heading_color",
        "label": "Heading",
        "default": "#1c1b1b"
      },
      {
        "type": "color",
        "id": "text_color",
        "label": "Body text",
        "default": "#677279"
      },
      {
        "type": "color",
        "id": "background",
        "label": "Background",
        "default": "#ffffff"
      },
      {
        "type": "color",
        "id": "secondary_background",
        "label": "Secondary background",
        "info": "Use a color close to the main background.",
        "default": "#f7f8fd"
      },
      {
        "type": "color",
        "id": "success_color",
        "label": "Success",
        "default": "#168342"
      },
      {
        "type": "color",
        "id": "error_color",
        "label": "Error",
        "default": "#e00000"
      },
      {
        "type": "header",
        "content": "Header"
      },
      {
        "type": "color",
        "id": "header_background",
        "label": "Background",
        "default": "#1e316a"
      },
      {
        "type": "color",
        "id": "header_text_color",
        "label": "Text",
        "default": "#ffffff"
      },
      {
        "type": "header",
        "content": "Footer"
      },
      {
        "type": "color",
        "id": "footer_background",
        "label": "Background",
        "default": "#f3f5f6"
      },
      {
        "type": "color",
        "id": "footer_text_color",
        "label": "Text",
        "default": "#677279"
      },
      {
        "type": "header",
        "content": "Primary button"
      },
      {
        "type": "color",
        "id": "primary_button_background",
        "label": "Background",
        "default": "#00badb"
      },
      {
        "type": "color",
        "id": "primary_button_text_color",
        "label": "Text",
        "default": "#ffffff"
      },
      {
        "type": "header",
        "content": "Secondary button"
      },
      {
        "type": "color",
        "id": "secondary_button_background",
        "label": "Background",
        "default": "#1e2d7d"
      },
      {
        "type": "color",
        "id": "secondary_button_text_color",
        "label": "Text",
        "default": "#ffffff"
      },
      {
        "type": "header",
        "content": "Product"
      },
      {
        "type": "color",
        "id": "product_rating_color",
        "label": "Star rating",
        "default": "#f6a429"
      },
      {
        "type": "color",
        "id": "product_on_sale_accent",
        "label": "On sale accent",
        "default": "#e00000"
      },
      {
        "type": "color",
        "id": "product_sold_out_accent",
        "label": "Sold out accent",
        "default": "#6f719b"
      },
      {
        "type": "color",
        "id": "product_custom_label_background",
        "label": "Custom label",
        "info": "[Learn more](https:\/\/support.maestrooo.com\/article\/75-collection-displaying-custom-label)",
        "default": "#1e316a"
      },
      {
        "type": "color",
        "id": "product_custom_label_2_background",
        "label": "Custom label 2",
        "info": "[Learn more](https:\/\/support.maestrooo.com\/article\/75-collection-displaying-custom-label)",
        "default": "#1e316a"
      },
      {
        "type": "color",
        "id": "product_in_stock_text_color",
        "label": "In stock accent",
        "default": "#168342"
      },
      {
        "type": "color",
        "id": "product_low_stock_text_color",
        "label": "Low stock accent",
        "default": "#e00000"
      }
    ]
  },
  {
    "name": "🟪 Typography (Go-To)",
    "settings": [
      {
        "type": "header",
        "content": "Headings"
      },
      {
        "type": "select",
        "id": "heading_font_size",
        "label": "Heading size",
        "options": [
          {
            "value": "small",
            "label": "Small"
          },
          {
            "value": "medium",
            "label": "Medium"
          },
          {
            "value": "large",
            "label": "Large"
          }
        ],
        "default": "medium"
      },
      {
        "type": "select",
        "id": "heading_text_transform",
        "label": "Heading style",
        "options": [
          {
            "value": "normal",
            "label": "Normal"
          },
          {
            "value": "lowercase",
            "label": "Lowercase"
          },
          {
            "value": "uppercase",
            "label": "Uppercase"
          }
        ],
        "default": "uppercase"
      },
      {
        "type": "header",
        "content": "Body text"
      },
      {
        "type": "range",
        "id": "text_font_size",
        "label": "Base size",
        "min": 12,
        "max": 20,
        "unit": "px",
        "default": 15
      }
    ]
  },
  {
    "name": "🟪 Social media (Go-To)",
    "settings": [
      {
        "type": "header",
        "content": "Accounts"
      },
      {
        "type": "text",
        "id": "social_facebook",
        "label": "Facebook"
      },
      {
        "type": "text",
        "id": "social_twitter",
        "label": "X (formerly Twitter)"
      },
      {
        "type": "text",
        "id": "social_threads",
        "label": "Threads"
      },
      {
        "type": "text",
        "id": "social_pinterest",
        "label": "Pinterest"
      },
      {
        "type": "text",
        "id": "social_instagram",
        "label": "Instagram"
      },
      {
        "type": "text",
        "id": "social_vimeo",
        "label": "Vimeo"
      },
      {
        "type": "text",
        "id": "social_tumblr",
        "label": "Tumblr"
      },
      {
        "type": "text",
        "id": "social_youtube",
        "label": "YouTube"
      },
      {
        "type": "text",
        "id": "social_tiktok",
        "label": "TikTok"
      },
      {
        "type": "text",
        "id": "social_linkedin",
        "label": "LinkedIn"
      },
      {
        "type": "text",
        "id": "social_snapchat",
        "label": "Snapchat"
      },
      {
        "type": "text",
        "id": "social_fancy",
        "label": "Fancy"
      },
      {
        "type": "text",
        "id": "social_wechat",
        "label": "WeChat"
      },
      {
        "type": "text",
        "id": "social_reddit",
        "label": "Reddit"
      },
      {
        "type": "text",
        "id": "social_line",
        "label": "LINE"
      },
      {
        "type": "text",
        "id": "social_spotify",
        "label": "Spotify"
      }
    ]
  },
  {
    "name": "🟪 Blog Tags (Go-To)",
    "settings": [
      {
        "type": "textarea",
        "id": "blog_tags_go-to",
        "label": "Blog Tags",
        "info": "An Array of article tags seperated by a comma."
      }
    ]
  },
  {
    "name": "🟥 Colors (Bro-To)",
    "settings": [
      {
        "type": "header",
        "content": "General"
      },
      {
        "type": "color",
        "id": "broto_heading_color",
        "label": "Heading",
        "default": "#1c1b1b"
      },
      {
        "type": "color",
        "id": "broto_text_color",
        "label": "Body text",
        "default": "#677279"
      },
      {
        "type": "color",
        "id": "broto_background",
        "label": "Background",
        "default": "#ffffff"
      },
      {
        "type": "color",
        "id": "broto_secondary_background",
        "label": "Secondary background",
        "info": "Use a color close to the main background.",
        "default": "#f7f8fd"
      },
      {
        "type": "color",
        "id": "broto_success_color",
        "label": "Success",
        "default": "#168342"
      },
      {
        "type": "color",
        "id": "broto_error_color",
        "label": "Error",
        "default": "#e00000"
      },
      {
        "type": "header",
        "content": "Header"
      },
      {
        "type": "color",
        "id": "broto_header_background",
        "label": "Background",
        "default": "#1e316a"
      },
      {
        "type": "color",
        "id": "broto_header_text_color",
        "label": "Text",
        "default": "#ffffff"
      },
      {
        "type": "header",
        "content": "Footer"
      },
      {
        "type": "color",
        "id": "broto_footer_background",
        "label": "Background",
        "default": "#f3f5f6"
      },
      {
        "type": "color",
        "id": "broto_footer_text_color",
        "label": "Text",
        "default": "#677279"
      },
      {
        "type": "header",
        "content": "Primary button"
      },
      {
        "type": "color",
        "id": "broto_primary_button_background",
        "label": "Background",
        "default": "#00badb"
      },
      {
        "type": "color",
        "id": "broto_primary_button_text_color",
        "label": "Text",
        "default": "#ffffff"
      },
      {
        "type": "header",
        "content": "Secondary button"
      },
      {
        "type": "color",
        "id": "broto_secondary_button_background",
        "label": "Background",
        "default": "#1e2d7d"
      },
      {
        "type": "color",
        "id": "broto_secondary_button_text_color",
        "label": "Text",
        "default": "#ffffff"
      },
      {
        "type": "header",
        "content": "Product"
      },
      {
        "type": "color",
        "id": "broto_product_rating_color",
        "label": "Star rating",
        "default": "#f6a429"
      },
      {
        "type": "color",
        "id": "broto_product_on_sale_accent",
        "label": "On sale accent",
        "default": "#e00000"
      },
      {
        "type": "color",
        "id": "broto_product_sold_out_accent",
        "label": "Sold out accent",
        "default": "#6f719b"
      },
      {
        "type": "color",
        "id": "broto_product_custom_label_background",
        "label": "Custom label",
        "info": "[Learn more](https:\/\/support.maestrooo.com\/article\/75-collection-displaying-custom-label)",
        "default": "#1e316a"
      },
      {
        "type": "color",
        "id": "broto_product_custom_label_2_background",
        "label": "Custom label 2",
        "info": "[Learn more](https:\/\/support.maestrooo.com\/article\/75-collection-displaying-custom-label)",
        "default": "#1e316a"
      },
      {
        "type": "color",
        "id": "broto_product_in_stock_text_color",
        "label": "In stock accent",
        "default": "#168342"
      },
      {
        "type": "color",
        "id": "broto_product_low_stock_text_color",
        "label": "Low stock accent",
        "default": "#e00000"
      }
    ]
  },
  {
    "name": "🟥 Typography (Bro-To)",
    "settings": [
      {
        "type": "header",
        "content": "Headings"
      },
      {
        "type": "select",
        "id": "broto_heading_font_size",
        "label": "Heading size",
        "options": [
          {
            "value": "small",
            "label": "Small"
          },
          {
            "value": "medium",
            "label": "Medium"
          },
          {
            "value": "large",
            "label": "Large"
          }
        ],
        "default": "medium"
      },
      {
        "type": "select",
        "id": "broto_heading_text_transform",
        "label": "Heading style",
        "options": [
          {
            "value": "normal",
            "label": "Normal"
          },
          {
            "value": "lowercase",
            "label": "Lowercase"
          },
          {
            "value": "uppercase",
            "label": "Uppercase"
          }
        ],
        "default": "uppercase"
      },
      {
        "type": "header",
        "content": "Body text"
      },
      {
        "type": "range",
        "id": "broto_text_font_size",
        "label": "Base size",
        "min": 12,
        "max": 20,
        "unit": "px",
        "default": 15
      }
    ]
  },
  {
    "name": "🟥 Social media (Bro-To)",
    "settings": [
      {
        "type": "header",
        "content": "Accounts"
      },
      {
        "type": "text",
        "id": "broto_social_facebook",
        "label": "Facebook"
      },
      {
        "type": "text",
        "id": "broto_social_twitter",
        "label": "X (formerly Twitter)"
      },
      {
        "type": "text",
        "id": "broto_social_threads",
        "label": "Threads"
      },
      {
        "type": "text",
        "id": "broto_social_pinterest",
        "label": "Pinterest"
      },
      {
        "type": "text",
        "id": "broto_social_instagram",
        "label": "Instagram"
      },
      {
        "type": "text",
        "id": "broto_social_vimeo",
        "label": "Vimeo"
      },
      {
        "type": "text",
        "id": "broto_social_tumblr",
        "label": "Tumblr"
      },
      {
        "type": "text",
        "id": "broto_social_youtube",
        "label": "YouTube"
      },
      {
        "type": "text",
        "id": "broto_social_tiktok",
        "label": "TikTok"
      },
      {
        "type": "text",
        "id": "broto_social_linkedin",
        "label": "LinkedIn"
      },
      {
        "type": "text",
        "id": "broto_social_snapchat",
        "label": "Snapchat"
      },
      {
        "type": "text",
        "id": "broto_social_fancy",
        "label": "Fancy"
      },
      {
        "type": "text",
        "id": "broto_social_wechat",
        "label": "WeChat"
      },
      {
        "type": "text",
        "id": "broto_social_reddit",
        "label": "Reddit"
      },
      {
        "type": "text",
        "id": "broto_social_line",
        "label": "LINE"
      },
      {
        "type": "text",
        "id": "broto_social_spotify",
        "label": "Spotify"
      }
    ]
  },
  {
    "name": "🟥 Blog Tags (Bro-To)",
    "settings": [
      {
        "type": "textarea",
        "id": "blog_tags_bro-to",
        "label": "Blog Tags",
        "info": "An Array of article tags seperated by a comma."
      }
    ]
  },
  {
    "name": "🟩 Colors (Gro-To)",
    "settings": [
      {
        "type": "header",
        "content": "General"
      },
      {
        "type": "color",
        "id": "groto_heading_color",
        "label": "Heading",
        "default": "#1c1b1b"
      },
      {
        "type": "color",
        "id": "groto_text_color",
        "label": "Body text",
        "default": "#677279"
      },
      {
        "type": "color",
        "id": "groto_background",
        "label": "Background",
        "default": "#ffffff"
      },
      {
        "type": "color",
        "id": "groto_secondary_background",
        "label": "Secondary background",
        "info": "Use a color close to the main background.",
        "default": "#f7f8fd"
      },
      {
        "type": "color",
        "id": "groto_success_color",
        "label": "Success",
        "default": "#168342"
      },
      {
        "type": "color",
        "id": "groto_error_color",
        "label": "Error",
        "default": "#e00000"
      },
      {
        "type": "header",
        "content": "Header"
      },
      {
        "type": "color",
        "id": "groto_header_background",
        "label": "Background",
        "default": "#1e316a"
      },
      {
        "type": "color",
        "id": "groto_header_text_color",
        "label": "Text",
        "default": "#ffffff"
      },
      {
        "type": "header",
        "content": "Footer"
      },
      {
        "type": "color",
        "id": "groto_footer_background",
        "label": "Background",
        "default": "#f3f5f6"
      },
      {
        "type": "color",
        "id": "groto_footer_text_color",
        "label": "Text",
        "default": "#677279"
      },
      {
        "type": "header",
        "content": "Primary button"
      },
      {
        "type": "color",
        "id": "groto_primary_button_background",
        "label": "Background",
        "default": "#00badb"
      },
      {
        "type": "color",
        "id": "groto_primary_button_text_color",
        "label": "Text",
        "default": "#ffffff"
      },
      {
        "type": "header",
        "content": "Secondary button"
      },
      {
        "type": "color",
        "id": "groto_secondary_button_background",
        "label": "Background",
        "default": "#1e2d7d"
      },
      {
        "type": "color",
        "id": "groto_secondary_button_text_color",
        "label": "Text",
        "default": "#ffffff"
      },
      {
        "type": "header",
        "content": "Product"
      },
      {
        "type": "color",
        "id": "groto_product_rating_color",
        "label": "Star rating",
        "default": "#f6a429"
      },
      {
        "type": "color",
        "id": "groto_product_on_sale_accent",
        "label": "On sale accent",
        "default": "#e00000"
      },
      {
        "type": "color",
        "id": "groto_product_sold_out_accent",
        "label": "Sold out accent",
        "default": "#6f719b"
      },
      {
        "type": "color",
        "id": "groto_product_custom_label_background",
        "label": "Custom label",
        "info": "[Learn more](https:\/\/support.maestrooo.com\/article\/75-collection-displaying-custom-label)",
        "default": "#1e316a"
      },
      {
        "type": "color",
        "id": "groto_product_custom_label_2_background",
        "label": "Custom label 2",
        "info": "[Learn more](https:\/\/support.maestrooo.com\/article\/75-collection-displaying-custom-label)",
        "default": "#1e316a"
      },
      {
        "type": "color",
        "id": "groto_product_in_stock_text_color",
        "label": "In stock accent",
        "default": "#168342"
      },
      {
        "type": "color",
        "id": "groto_product_low_stock_text_color",
        "label": "Low stock accent",
        "default": "#e00000"
      }
    ]
  },
  {
    "name": "🟩 Typography (Gro-To)",
    "settings": [
      {
        "type": "header",
        "content": "Headings"
      },
      {
        "type": "select",
        "id": "groto_heading_font_size",
        "label": "Heading size",
        "options": [
          {
            "value": "small",
            "label": "Small"
          },
          {
            "value": "medium",
            "label": "Medium"
          },
          {
            "value": "large",
            "label": "Large"
          }
        ],
        "default": "medium"
      },
      {
        "type": "select",
        "id": "groto_heading_text_transform",
        "label": "Heading style",
        "options": [
          {
            "value": "normal",
            "label": "Normal"
          },
          {
            "value": "lowercase",
            "label": "Lowercase"
          },
          {
            "value": "uppercase",
            "label": "Uppercase"
          }
        ],
        "default": "uppercase"
      },
      {
        "type": "header",
        "content": "Body text"
      },
      {
        "type": "range",
        "id": "groto_text_font_size",
        "label": "Base size",
        "min": 12,
        "max": 20,
        "unit": "px",
        "default": 15
      }
    ]
  },
  {
    "name": "🟩 Social media (Gro-To)",
    "settings": [
      {
        "type": "header",
        "content": "Accounts"
      },
      {
        "type": "text",
        "id": "groto_social_facebook",
        "label": "Facebook"
      },
      {
        "type": "text",
        "id": "groto_social_twitter",
        "label": "X (formerly Twitter)"
      },
      {
        "type": "text",
        "id": "groto_social_threads",
        "label": "Threads"
      },
      {
        "type": "text",
        "id": "groto_social_pinterest",
        "label": "Pinterest"
      },
      {
        "type": "text",
        "id": "groto_social_instagram",
        "label": "Instagram"
      },
      {
        "type": "text",
        "id": "groto_social_vimeo",
        "label": "Vimeo"
      },
      {
        "type": "text",
        "id": "groto_social_tumblr",
        "label": "Tumblr"
      },
      {
        "type": "text",
        "id": "groto_social_youtube",
        "label": "YouTube"
      },
      {
        "type": "text",
        "id": "groto_social_tiktok",
        "label": "TikTok"
      },
      {
        "type": "text",
        "id": "groto_social_linkedin",
        "label": "LinkedIn"
      },
      {
        "type": "text",
        "id": "groto_social_snapchat",
        "label": "Snapchat"
      },
      {
        "type": "text",
        "id": "groto_social_fancy",
        "label": "Fancy"
      },
      {
        "type": "text",
        "id": "groto_social_wechat",
        "label": "WeChat"
      },
      {
        "type": "text",
        "id": "groto_social_reddit",
        "label": "Reddit"
      },
      {
        "type": "text",
        "id": "groto_social_line",
        "label": "LINE"
      },
      {
        "type": "text",
        "id": "groto_social_spotify",
        "label": "Spotify"
      }
    ]
  },
  {
    "name": "🟩 Blog Tags (Gro-To)",
    "settings": [
      {
        "type": "textarea",
        "id": "blog_tags_gro-to",
        "label": "Blog Tags",
        "info": "An Array of article tags seperated by a comma."
      }
    ]
  },
  {
    "name": "Appearance",
    "settings": [
      {
        "type": "paragraph",
        "content": "Adapt the theme to your brand style by changing rounded elements, spacing and icons style."
      },
      {
        "type": "range",
        "id": "icon_stroke_width",
        "min": 1,
        "max": 2,
        "step": 0.1,
        "unit": "px",
        "label": "Icon thickness",
        "default": 2
      },
      {
        "type": "range",
        "id": "button_border_radius",
        "min": 0,
        "max": 30,
        "step": 2,
        "unit": "px",
        "label": "Button\/input border radius",
        "default": 0
      },
      {
        "type": "select",
        "id": "block_border_radius",
        "label": "Block border radius",
        "options": [
          {
            "value": "none",
            "label": "None"
          },
          {
            "value": "small",
            "label": "Small"
          },
          {
            "value": "medium",
            "label": "Medium"
          },
          {
            "value": "large",
            "label": "Large"
          }
        ],
        "default": "none"
      },
      {
        "type": "select",
        "id": "vertical_spacing",
        "label": "Vertical spacing",
        "info": "Impact the vertical spacing separating each section.",
        "options": [
          {
            "value": "small",
            "label": "Small"
          },
          {
            "value": "medium",
            "label": "Medium"
          },
          {
            "value": "large",
            "label": "Large"
          }
        ],
        "default": "large"
      }
    ]
  },
  {
    "name": "Currency format",
    "settings": [
      {
        "type": "header",
        "content": "Currency codes"
      },
      {
        "type": "paragraph",
        "content": "Cart and checkout prices always show currency codes. Example: $1.00 USD."
      },
      {
        "type": "checkbox",
        "id": "currency_code_enabled",
        "label": "Show currency codes",
        "default": false
      }
    ]
  },
  {
    "name": "Animation",
    "settings": [
      {
        "type": "paragraph",
        "content": "Users who configured their preferences to minimize non-essential motion will automatically experience reduced animations."
      },
      {
        "type": "checkbox",
        "id": "show_image_zoom",
        "label": "Show image zoom",
        "info": "Affect various images that are slowly zoomed on hover",
        "default": true
      },
      {
        "type": "checkbox",
        "id": "stagger_products_apparition",
        "label": "Reveal products one by one",
        "info": "Affect any product grid listing",
        "default": true
      },
      {
        "type": "checkbox",
        "id": "stagger_blog_posts_apparition",
        "label": "Reveal blog posts one by one",
        "info": "Affect any blog post listing",
        "default": true
      },
      {
        "type": "checkbox",
        "id": "reveal_product_media",
        "label": "Reveal product media",
        "info": "Affect product pages and featured product section",
        "default": true
      }
    ]
  },
  {
    "name": "Color swatch",
    "settings": [
      {
        "type": "checkbox",
        "id": "round_color_swatches",
        "label": "Round color swatches",
        "default": false
      },
      {
        "type": "textarea",
        "id": "color_swatch_config",
        "label": "Configuration (deprecated)",
        "placeholder": "Red:#ff0000\nGreen:#00ff00\nBlue:#0000ff",
        "info": "Native color swatch should be used instead. [Learn more](https:\/\/help.shopify.com\/en\/manual\/online-store\/themes\/theme-structure\/theme-settings#options-with-swatches). Configuration based color swatches is deprecated and will be removed in the future. If you still need to use the configuration based system, you can [learn more](https:\/\/support.maestrooo.com\/article\/80-product-uploading-custom-color-for-color-swatch) about the exact naming convention."
      }
    ]
  },
  {
    "name": "Products grid",
    "settings": [
      {
        "type": "checkbox",
        "id": "show_vendor",
        "label": "Show vendor",
        "default": false
      },
      {
        "type": "checkbox",
        "id": "show_secondary_image",
        "label": "Show secondary image on hover",
        "default": false
      },
      {
        "type": "checkbox",
        "id": "product_add_to_cart",
        "label": "Enable quick add to cart",
        "default": true
      },
      {
        "type": "checkbox",
        "id": "show_product_rating",
        "label": "Show product rating",
        "info": "To display a rating, add a product rating app. [Learn more](https:\/\/help.shopify.com\/en\/manual\/products\/product-reviews\/installation)",
        "default": false
      },
      {
        "type": "checkbox",
        "id": "show_discount",
        "label": "Show discount label",
        "default": true
      },
      {
        "type": "select",
        "id": "discount_mode",
        "label": "Show discount as...",
        "options": [
          {
            "value": "percentage",
            "label": "Percentage"
          },
          {
            "value": "saving",
            "label": "Saving"
          }
        ],
        "default": "saving"
      },
      {
        "type": "select",
        "id": "product_color_display",
        "label": "Color display mode",
        "options": [
          {
            "value": "hide",
            "label": "Hide"
          },
          {
            "value": "count",
            "label": "Count"
          },
          {
            "value": "swatch",
            "label": "Swatch"
          }
        ],
        "default": "count"
      },
      {
        "type": "select",
        "id": "product_image_size",
        "label": "Product image size",
        "options": [
          {
            "value": "natural",
            "label": "Natural"
          },
          {
            "value": "short",
            "label": "Short (4:3)"
          },
          {
            "value": "square",
            "label": "Square (1:1)"
          },
          {
            "value": "tall",
            "label": "Tall (2:3)"
          }
        ],
        "default": "natural"
      }
    ]
  },
  {
    "name": "Cart",
    "settings": [
      {
        "type": "select",
        "id": "cart_type",
        "label": "Cart type",
        "options": [
          {
            "value": "drawer",
            "label": "Drawer"
          },
          {
            "value": "message",
            "label": "Message"
          },
          {
            "value": "page",
            "label": "Page"
          }
        ],
        "default": "message"
      },
      {
        "type": "select",
        "id": "cart_icon",
        "label": "Cart icon",
        "options": [
          {
            "value": "shopping_bag",
            "label": "Shopping bag"
          },
          {
            "value": "shopping_cart",
            "label": "Shopping cart"
          },
          {
            "value": "tote_bag",
            "label": "Tote bag"
          },
          {
            "value": "go-to-bag",
            "label": "Go-To bag"
          }
        ],
        "default": "shopping_bag"
      },
      {
        "type": "header",
        "content": "Shipping Motivator (AU 🇦🇺)"
      },
      {
        "type": "checkbox",
        "id": "shipping_motivator_AU",
        "label": "(🟪 Go-To) Show For Australia?"
      },
      {
        "type": "checkbox",
        "id": "shipping_motivator_AU_bro",
        "label": "(🟥 Bro-To) Show For Australia?"
      },
        {
        "type": "checkbox",
        "id": "shipping_motivator_AU_gro",
        "label": "(🟩 Gro-To) Show For Australia?"
      },
      {
        "type": "text",
        "id": "cart_free_shipping_threshold",
        "label": "Free shipping minimum amount",
        "default": "50"
      },
      {
        "type": "header",
        "content": "Shipping Motivator (NZ 🇳🇿)"
      },
         {
        "type": "checkbox",
        "id": "shipping_motivator_NZ",
        "label": "(🟪 Go-To) Show For NZ?"
      },
      {
        "type": "checkbox",
        "id": "shipping_motivator_NZ_bro",
        "label": "(🟥 Bro-To) Show For NZ?"
      },
        {
        "type": "checkbox",
        "id": "shipping_motivator_NZ_gro",
        "label": "(🟩 Gro-To) Show For NZ?"
      },
      {
        "type": "text",
        "id": "cart_free_shipping_threshold_NZ",
        "label": "Free shipping minimum amount",
        "default": "50"
      },
      {
        "type": "header",
        "content": "Shipping Motivator (UK 🇬🇧)"
      },
      {
        "type": "checkbox",
        "id": "shipping_motivator_UK",
        "label": "(🟪 Go-To) Show For UK?"
      },
      {
        "type": "checkbox",
        "id": "shipping_motivator_UK_bro",
        "label": "(🟥 Bro-To) Show For UK?"
      },
        {
        "type": "checkbox",
        "id": "shipping_motivator_UK_gro",
        "label": "(🟩 Gro-To) Show For UK?"
      },
      {
        "type": "text",
        "id": "cart_free_shipping_threshold_GB",
        "label": "Free shipping minimum amount",
        "default": "50"
      },
      {
        "type": "header",
        "content": "Shipping Motivator (US 🇺🇸)"
      },
      {
        "type": "checkbox",
        "id": "shipping_motivator_US",
        "label": "(🟪 Go-To) Show For US?"
      },
      {
        "type": "checkbox",
        "id": "shipping_motivator_US_bro",
        "label": "(🟥 Bro-To) Show For US?"
      },
        {
        "type": "checkbox",
        "id": "shipping_motivator_US_gro",
        "label": "(🟩 Gro-To) Show For US?"
      },
      {
        "type": "text",
        "id": "cart_free_shipping_threshold_US",
        "label": "Free shipping minimum amount",
        "default": "50"
      },
      {
        "type": "header",
        "content": "Shipping Motivator (Text Size)"
      },
      {
        "type": "range",
        "id": "shipping_motivator_size_mobile",
        "min": 1,
        "max": 100,
        "step": 1,
        "unit": "px",
        "label": "Font Size (Mobile)",
        "default": 14
      },
      {
        "type": "range",
        "id": "shipping_motivator_size_desktop",
        "min": 1,
        "max": 100,
        "step": 1,
        "unit": "px",
        "label": "Font Size (Desktop)",
        "default": 14
      }
    ]
  },
  {
    "name": "Favicon",
    "settings": [
      {
        "type": "image_picker",
        "id": "favicon",
        "label": "Image",
        "info": "96 x 96px .png recommended"
      }
    ]
  },
  {
    "name": "Theme effects",
    "settings": [
      {
        "type": "header",
        "content": "Confetti"
      },
      {
        "type": "checkbox",
        "id": "show_confetti",
        "label": "Show confetti on theme",
        "default": false
      },
      {
        "type": "text",
        "id": "confetti_colors",
        "label": "Comma-separated hex colours of the confetti you want",
        "info": "E.g.: '#ffd400','#f58220','#ef5ba1','#ef4123','#b493c4','#39bb9d','#14b1e7'"
      },
      {
        "type": "text",
        "id": "show_confetti_on_template",
        "label": "Comma-separated template names where to show confetti",
        "info": "E.g.: product.go-to-face-hero-extra. If want to show on homepage use 'index.'. Show on all product pages use 'product.'"
      },
      {
        "type": "header",
        "content": "Glitter"
      },
      {
        "type": "checkbox",
        "id": "show_glitter",
        "label": "Show glitter effects on theme",
        "default": false
      },
      {
        "type": "text",
        "id": "show_glitter_on_template",
        "label": "Comma-separated template suffix names where to show glitter",
        "info": "E.g.: product.go-to-face-hero-extra. If want to show on homepage use 'index.'. Show on all product pages use 'product.'"
      },
      {
        "type": "range",
        "id": "glitter_count",
        "label": "Count",
        "min": 200,
        "max": 1000,
        "step": 10,
        "default": 200
      },
      {
        "type": "range",
        "id": "glitter_frequency",
        "label": "Frequency",
        "min": 1,
        "max": 50,
        "default": 10,
        "step": 1
      }
    ]
  },
  {
    "name": "Exclude Tags From Cart",
    "settings": [
      {
        "type": "textarea",
        "id": "exclude_product_tags_from_cart",
        "label": "Array of Tags",
        "info": "Comma Seperated e.g. badge_,skintype_ use Shift + Enter to add a new line."
      }
    ]
  },
  {
    "name": "Hide Pages From SEO",
    "settings": [
      {
        "type": "textarea",
        "id": "hide_seo_collections",
        "label": "Array Of Collection Handles",
        "info": "Comma Seperated e.g. face-hero,skintype"
      },
      {
        "type": "textarea",
        "id": "hide_seo_pages",
        "label": "Array Of Page Handles",
        "info": "Comma Seperated e.g. face-hero,skintype"
      }
    ]
  }
]
